[
  {
    "timestamp": "2026-05-01T13:58:04Z",
    "ticker": "AXSM",
    "news": "FDA approved AUVELITY for treatment of agitation associated with dementia due to Alzheimer's disease, marking the first-in-class NMDA/sigma-1 receptor therapy approval for this indication.",
    "source": "https://www.pharmaceutical-business-review.com/news/axsome-fda-approval-auvelity-alzheimers-agitation/",
    "changes": [
      {
        "path": "scenarios.base.assumptions.axs05_ad.ad_agit.pos",
        "old_value": 75,
        "new_value": 100,
        "reason": "FDA approval confirms probability of success is now 100%",
        "old_actual": 75
      },
      {
        "path": "scenarios.base.assumptions.axs05_ad.ad_agit.apr",
        "old_value": 85,
        "new_value": 100,
        "reason": "FDA approval confirms regulatory success is now 100%",
        "old_actual": 85
      },
      {
        "path": "scenarios.bear.assumptions.axs05_ad.ad_agit.pos",
        "old_value": 70,
        "new_value": 100,
        "reason": "FDA approval confirms probability of success is now 100%",
        "old_actual": 70
      },
      {
        "path": "scenarios.bear.assumptions.axs05_ad.ad_agit.apr",
        "old_value": 80,
        "new_value": 100,
        "reason": "FDA approval confirms regulatory success is now 100%",
        "old_actual": 80
      },
      {
        "path": "scenarios.bull.assumptions.axs05_ad.ad_agit.pos",
        "old_value": 80,
        "new_value": 100,
        "reason": "FDA approval confirms probability of success is now 100%",
        "old_actual": 80
      },
      {
        "path": "scenarios.bull.assumptions.axs05_ad.ad_agit.apr",
        "old_value": 90,
        "new_value": 100,
        "reason": "FDA approval confirms regulatory success is now 100%",
        "old_actual": 90
      },
      {
        "path": "scenarios.mega_bear.assumptions.axs05_ad.ad_agit.pos",
        "old_value": 70,
        "new_value": 100,
        "reason": "FDA approval confirms probability of success is now 100%",
        "old_actual": 70
      },
      {
        "path": "scenarios.mega_bear.assumptions.axs05_ad.ad_agit.apr",
        "old_value": 20,
        "new_value": 100,
        "reason": "FDA approval confirms regulatory success is now 100%",
        "old_actual": 20
      },
      {
        "path": "scenarios.psychedelic_bull.assumptions.axs05_ad.ad_agit.pos",
        "old_value": 90,
        "new_value": 100,
        "reason": "FDA approval confirms probability of success is now 100%",
        "old_actual": 90
      },
      {
        "path": "scenarios.psychedelic_bull.assumptions.axs05_ad.ad_agit.apr",
        "old_value": 95,
        "new_value": 100,
        "reason": "FDA approval confirms regulatory success is now 100%",
        "old_actual": 95
      },
      {
        "path": "catalysts.1.dateSort",
        "old_value": "2026-04-30",
        "new_value": "2026-04-14",
        "reason": "PDUFA decision occurred earlier than expected date",
        "old_actual": "2026-04-30"
      },
      {
        "path": "catalysts.1.date",
        "old_value": "April 30, 2026",
        "new_value": "Apr 14, 2026",
        "reason": "PDUFA decision occurred earlier than expected date",
        "old_actual": "April 30, 2026"
      }
    ]
  },
  {
    "timestamp": "2026-05-01T13:58:04Z",
    "ticker": "AZN",
    "news": "FDA advisory panel voted 6-3 against approval of AstraZeneca's oral breast cancer drug camizestrant due to concerns about trial design and long-term patient benefit demonstration.",
    "source": "https://www.cnbc.com/2026/05/01/astrazeneca-stock-az-fda-panel-cancer-drug.html",
    "changes": [
      {
        "path": "scenarios.base.assumptions.camizestrant.er_breast.pos",
        "old_value": 96,
        "new_value": 20,
        "reason": "Negative FDA advisory panel vote (6-3 against) significantly reduces approval probability",
        "old_actual": 96
      },
      {
        "path": "scenarios.base.assumptions.camizestrant.er_breast.apr",
        "old_value": 95,
        "new_value": 25,
        "reason": "Panel concerns about trial design and patient benefit demonstration lower approval chances",
        "old_actual": 95
      },
      {
        "path": "scenarios.bear.assumptions.camizestrant.er_breast.pos",
        "old_value": 88,
        "new_value": 15,
        "reason": "Negative advisory panel makes approval unlikely in bear case",
        "old_actual": 88
      },
      {
        "path": "scenarios.bear.assumptions.camizestrant.er_breast.apr",
        "old_value": 90,
        "new_value": 20,
        "reason": "Trial design concerns reduce approval probability",
        "old_actual": 90
      },
      {
        "path": "scenarios.bull.assumptions.camizestrant.er_breast.pos",
        "old_value": 99,
        "new_value": 35,
        "reason": "Even in bull case, negative panel vote creates significant regulatory risk",
        "old_actual": 99
      },
      {
        "path": "scenarios.bull.assumptions.camizestrant.er_breast.apr",
        "old_value": 97,
        "new_value": 40,
        "reason": "Panel concerns about demonstrating patient benefit reduce approval odds",
        "old_actual": 97
      },
      {
        "path": "catalysts.1.dateSort",
        "old_value": "2026-06-30",
        "new_value": "2026-05-01",
        "reason": "Advisory panel meeting occurred on May 1, 2026",
        "old_actual": "2026-06-30"
      },
      {
        "path": "catalysts.1.date",
        "old_value": "H1 2026",
        "new_value": "May 1, 2026",
        "reason": "Specific date of advisory panel meeting",
        "old_actual": "H1 2026"
      }
    ]
  },
  {
    "timestamp": "2026-05-01T13:58:04Z",
    "ticker": "KYMR",
    "news": "Kymera reported Q1 2026 results with $1.55 billion cash and received $45 million milestone from Gilead for exercising option on CDK2 molecular glue degrader KT-200 for breast cancer.",
    "source": "https://www.biospace.com/press-releases/kymera-therapeutics-announces-first-quarter-2026-financial-results-and-provides-a-business-update",
    "changes": [
      {
        "path": "company.cash",
        "old_value": 1645,
        "new_value": 1550,
        "reason": "Updated to Q1 2026 reported cash of $1.55B",
        "old_actual": 1645
      },
      {
        "path": "scenarios.base.assumptions.cdk2.onc.pos",
        "old_value": 25,
        "new_value": 35,
        "reason": "Gilead exercised option on CDK2 program, increasing probability of success",
        "old_actual": 25
      },
      {
        "path": "scenarios.bear.assumptions.cdk2.onc.pos",
        "old_value": 18,
        "new_value": 25,
        "reason": "Option exercise de-risks program even in bear case",
        "old_actual": 18
      },
      {
        "path": "scenarios.bull.assumptions.cdk2.onc.pos",
        "old_value": 35,
        "new_value": 45,
        "reason": "Option exercise validates CDK2 approach, boosting bull case probability",
        "old_actual": 35
      }
    ]
  },
  {
    "timestamp": "2026-05-01T13:58:04Z",
    "ticker": "MRK",
    "news": "Merck reported Q1 2026 sales of $16.3 billion with FDA approval for IDVYNSO HIV treatment and positive Phase 3 cardio-pulmonary data, plus announced acquisition of Terns Pharmaceuticals.",
    "source": "https://www.merck.com/news/merck-co-inc-rahway-n-j-usa-announces-first-quarter-2026-financial-results-highlights-significant-regulatory-approvals-and-clinical-milestones/",
    "changes": [
      {
        "path": "scenarios.base.assumptions.winrevair.pah.pos",
        "old_value": 100,
        "new_value": 100,
        "reason": "Positive Phase 3 cardio-pulmonary data supports current approval probability",
        "old_actual": 100
      },
      {
        "path": "scenarios.base.assumptions.winrevair.pah.pen",
        "old_value": 1.2,
        "new_value": 1.3,
        "reason": "Positive Phase 3 cardio-pulmonary data suggests potential for broader label expansion and increased market penetration",
        "old_actual": 1.2
      },
      {
        "path": "scenarios.bull.assumptions.winrevair.pah.pen",
        "old_value": 1.4,
        "new_value": 1.5,
        "reason": "Strong cardio-pulmonary data supports bull case for expanded indications beyond PAH",
        "old_actual": 1.4
      },
      {
        "path": "scenarios.bear.assumptions.winrevair.pah.pen",
        "old_value": 1.0,
        "new_value": 1.1,
        "reason": "Even in bear case, positive cardio-pulmonary data provides modest upside to penetration",
        "old_actual": 1.0
      }
    ]
  },
  {
    "timestamp": "2026-05-01T13:58:04Z",
    "ticker": "MRNA",
    "news": "Moderna reported strong Q1 2026 revenue of $389M (260% growth) with EU approvals for mCOMBRIAX flu/COVID combo vaccine and initiated Phase 3 study for intismeran in lung cancer.",
    "source": "https://www.bloomberg.com/news/articles/2026-05-01/moderna-mrna-beats-estimates-on-covid-vaccine-sales-outside-the-us",
    "changes": [
      {
        "path": "scenarios.base.assumptions.mrna_1083.combo.pos",
        "old_value": 70,
        "new_value": 80,
        "reason": "EU approval for mCOMBRIAX (flu/COVID combo) significantly de-risks regulatory pathway",
        "old_actual": 70
      },
      {
        "path": "scenarios.bear.assumptions.mrna_1083.combo.pos",
        "old_value": 50,
        "new_value": 65,
        "reason": "EU approval for mCOMBRIAX provides regulatory validation for combo approach",
        "old_actual": 50
      },
      {
        "path": "scenarios.bull.assumptions.mrna_1083.combo.pos",
        "old_value": 85,
        "new_value": 90,
        "reason": "EU approval for mCOMBRIAX further supports high confidence scenario",
        "old_actual": 85
      },
      {
        "path": "scenarios.base.assumptions.intismeran.nsclc_adj.pos",
        "old_value": 50,
        "new_value": 55,
        "reason": "Initiation of Phase 3 study in lung cancer demonstrates continued development commitment",
        "old_actual": 50
      },
      {
        "path": "scenarios.base.val.commercialRevM",
        "old_value": 1930,
        "new_value": 2100,
        "reason": "Q1 revenue beat of $389M suggests stronger commercial performance trajectory",
        "old_actual": 1930
      }
    ]
  }
]